ncd_classifier/__init__.py
ncd_classifier/compressors.py
ncd_classifier/ncd_classifier.py
ncd_classifier-0.1.1.dist-info/METADATA
ncd_classifier-0.1.1.dist-info/WHEEL
ncd_classifier-0.1.1.dist-info/RECORD
